{"chapters": [{"url": "http://ctext.org/book-of-changes/yi-jing/zh", "ch_name": "易經", "en_name": "yi-jing", "id": 1, "articles": [1, 2, 3, 4, 5, 6, 7, 8, 9, 10, 11, 12, 13, 14, 15, 16, 17, 18, 19, 20, 21, 22, 23, 24, 25, 26, 27, 28, 29, 30, 31, 32, 33, 34, 35, 36, 37, 38, 39, 40, 41, 42, 43, 44, 45, 46, 47, 48, 49, 50, 51, 52, 53, 54, 55, 56, 57, 58, 59, 60, 61, 62, 63, 64]}, {"url": "http://ctext.org/book-of-changes/tuan-zhuan/zh", "ch_name": "彖傳", "en_name": "tuan-zhuan", "id": 2, "articles": [65, 66, 67, 68, 69, 70, 71, 72, 73, 74, 75, 76, 77, 78, 79, 80, 81, 82, 83, 84, 85, 86, 87, 88, 89, 90, 91, 92, 93, 94, 95, 96, 97, 98, 99, 100, 101, 102, 103, 104, 105, 106, 107, 108, 109, 110, 111, 112, 113, 114, 115, 116, 117, 118, 119, 120, 121, 122, 123, 124, 125, 126, 127, 128]}, {"url": "http://ctext.org/book-of-changes/xiang-zhuan/zh", "ch_name": "象傳", "en_name": "xiang-zhuan", "id": 3, "articles": [129, 130, 131, 132, 133, 134, 135, 136, 137, 138, 139, 140, 141, 142, 143, 144, 145, 146, 147, 148, 149, 150, 151, 152, 153, 154, 155, 156, 157, 158, 159, 160, 161, 162, 163, 164, 165, 166, 167, 168, 169, 170, 171, 172, 173, 174, 175, 176, 177, 178, 179, 180, 181, 182, 183, 184, 185, 186, 187, 188, 189, 190, 191, 192]}, {"url": "http://ctext.org/book-of-changes/wen-yan/zh", "ch_name": "文言", "en_name": "wen-yan", "id": 4, "articles": [193, 194]}], "articles": {"1": {"chapter_id": 1, "url": "http://ctext.org/book-of-changes/qian/zh", "en_name": "qian", "ch_name": "䷀乾"}, "2": {"chapter_id": 1, "url": "http://ctext.org/book-of-changes/kun/zh", "en_name": "kun", "ch_name": "䷁坤"}, "3": {"chapter_id": 1, "url": "http://ctext.org/book-of-changes/zhun/zh", "en_name": "zhun", "ch_name": "䷂屯"}, "4": {"chapter_id": 1, "url": "http://ctext.org/book-of-changes/meng/zh", "en_name": "meng", "ch_name": "䷃蒙"}, "5": {"chapter_id": 1, "url": "http://ctext.org/book-of-changes/xu/zh", "en_name": "xu", "ch_name": "䷄需"}, "6": {"chapter_id": 1, "url": "http://ctext.org/book-of-changes/song/zh", "en_name": "song", "ch_name": "䷅訟"}, "7": {"chapter_id": 1, "url": "http://ctext.org/book-of-changes/shi/zh", "en_name": "shi", "ch_name": "䷆師"}, "8": {"chapter_id": 1, "url": "http://ctext.org/book-of-changes/bi/zh", "en_name": "bi", "ch_name": "䷇比"}, "9": {"chapter_id": 1, "url": "http://ctext.org/book-of-changes/xiao-xu/zh", "en_name": "xiao-xu", "ch_name": "䷈小畜"}, "10": {"chapter_id": 1, "url": "http://ctext.org/book-of-changes/lu/zh", "en_name": "lu", "ch_name": "䷉履"}, "11": {"chapter_id": 1, "url": "http://ctext.org/book-of-changes/tai/zh", "en_name": "tai", "ch_name": "䷊泰"}, "12": {"chapter_id": 1, "url": "http://ctext.org/book-of-changes/pi/zh", "en_name": "pi", "ch_name": "䷋否"}, "13": {"chapter_id": 1, "url": "http://ctext.org/book-of-changes/tong-ren/zh", "en_name": "tong-ren", "ch_name": "䷌同人"}, "14": {"chapter_id": 1, "url": "http://ctext.org/book-of-changes/da-you/zh", "en_name": "da-you", "ch_name": "䷍大有"}, "15": {"chapter_id": 1, "url": "http://ctext.org/book-of-changes/qian1/zh", "en_name": "qian1", "ch_name": "䷎謙"}, "16": {"chapter_id": 1, "url": "http://ctext.org/book-of-changes/yu/zh", "en_name": "yu", "ch_name": "䷏豫"}, "17": {"chapter_id": 1, "url": "http://ctext.org/book-of-changes/sui/zh", "en_name": "sui", "ch_name": "䷐隨"}, "18": {"chapter_id": 1, "url": "http://ctext.org/book-of-changes/gu/zh", "en_name": "gu", "ch_name": "䷑蠱"}, "19": {"chapter_id": 1, "url": "http://ctext.org/book-of-changes/lin/zh", "en_name": "lin", "ch_name": "䷒臨"}, "20": {"chapter_id": 1, "url": "http://ctext.org/book-of-changes/guan/zh", "en_name": "guan", "ch_name": "䷓觀"}, "21": {"chapter_id": 1, "url": "http://ctext.org/book-of-changes/shi-he/zh", "en_name": "shi-he", "ch_name": "䷔噬嗑"}, "22": {"chapter_id": 1, "url": "http://ctext.org/book-of-changes/bi1/zh", "en_name": "bi1", "ch_name": "䷕賁"}, "23": {"chapter_id": 1, "url": "http://ctext.org/book-of-changes/bo/zh", "en_name": "bo", "ch_name": "䷖剝"}, "24": {"chapter_id": 1, "url": "http://ctext.org/book-of-changes/fu/zh", "en_name": "fu", "ch_name": "䷗復"}, "25": {"chapter_id": 1, "url": "http://ctext.org/book-of-changes/wu-wang/zh", "en_name": "wu-wang", "ch_name": "䷘无妄"}, "26": {"chapter_id": 1, "url": "http://ctext.org/book-of-changes/da-xu/zh", "en_name": "da-xu", "ch_name": "䷙大畜"}, "27": {"chapter_id": 1, "url": "http://ctext.org/book-of-changes/yi/zh", "en_name": "yi", "ch_name": "䷚頤"}, "28": {"chapter_id": 1, "url": "http://ctext.org/book-of-changes/da-guo/zh", "en_name": "da-guo", "ch_name": "䷛大過"}, "29": {"chapter_id": 1, "url": "http://ctext.org/book-of-changes/kan/zh", "en_name": "kan", "ch_name": "䷜坎"}, "30": {"chapter_id": 1, "url": "http://ctext.org/book-of-changes/li/zh", "en_name": "li", "ch_name": "䷝離"}, "31": {"chapter_id": 1, "url": "http://ctext.org/book-of-changes/xian/zh", "en_name": "xian", "ch_name": "䷞咸"}, "32": {"chapter_id": 1, "url": "http://ctext.org/book-of-changes/heng/zh", "en_name": "heng", "ch_name": "䷟恆"}, "33": {"chapter_id": 1, "url": "http://ctext.org/book-of-changes/dun/zh", "en_name": "dun", "ch_name": "䷠遯"}, "34": {"chapter_id": 1, "url": "http://ctext.org/book-of-changes/da-zhuang/zh", "en_name": "da-zhuang", "ch_name": "䷡大壯"}, "35": {"chapter_id": 1, "url": "http://ctext.org/book-of-changes/jin/zh", "en_name": "jin", "ch_name": "䷢晉"}, "36": {"chapter_id": 1, "url": "http://ctext.org/book-of-changes/ming-yi/zh", "en_name": "ming-yi", "ch_name": "䷣明夷"}, "37": {"chapter_id": 1, "url": "http://ctext.org/book-of-changes/jia-ren/zh", "en_name": "jia-ren", "ch_name": "䷤家人"}, "38": {"chapter_id": 1, "url": "http://ctext.org/book-of-changes/kui/zh", "en_name": "kui", "ch_name": "䷥睽"}, "39": {"chapter_id": 1, "url": "http://ctext.org/book-of-changes/jian/zh", "en_name": "jian", "ch_name": "䷦蹇"}, "40": {"chapter_id": 1, "url": "http://ctext.org/book-of-changes/jie/zh", "en_name": "jie", "ch_name": "䷧解"}, "41": {"chapter_id": 1, "url": "http://ctext.org/book-of-changes/sun/zh", "en_name": "sun", "ch_name": "䷨損"}, "42": {"chapter_id": 1, "url": "http://ctext.org/book-of-changes/yi1/zh", "en_name": "yi1", "ch_name": "䷩益"}, "43": {"chapter_id": 1, "url": "http://ctext.org/book-of-changes/guai/zh", "en_name": "guai", "ch_name": "䷪夬"}, "44": {"chapter_id": 1, "url": "http://ctext.org/book-of-changes/gou/zh", "en_name": "gou", "ch_name": "䷫姤"}, "45": {"chapter_id": 1, "url": "http://ctext.org/book-of-changes/cui/zh", "en_name": "cui", "ch_name": "䷬萃"}, "46": {"chapter_id": 1, "url": "http://ctext.org/book-of-changes/sheng/zh", "en_name": "sheng", "ch_name": "䷭升"}, "47": {"chapter_id": 1, "url": "http://ctext.org/book-of-changes/kun1/zh", "en_name": "kun1", "ch_name": "䷮困"}, "48": {"chapter_id": 1, "url": "http://ctext.org/book-of-changes/jing/zh", "en_name": "jing", "ch_name": "䷯井"}, "49": {"chapter_id": 1, "url": "http://ctext.org/book-of-changes/ge/zh", "en_name": "ge", "ch_name": "䷰革"}, "50": {"chapter_id": 1, "url": "http://ctext.org/book-of-changes/ding/zh", "en_name": "ding", "ch_name": "䷱鼎"}, "51": {"chapter_id": 1, "url": "http://ctext.org/book-of-changes/zhen/zh", "en_name": "zhen", "ch_name": "䷲震"}, "52": {"chapter_id": 1, "url": "http://ctext.org/book-of-changes/gen/zh", "en_name": "gen", "ch_name": "䷳艮"}, "53": {"chapter_id": 1, "url": "http://ctext.org/book-of-changes/jian1/zh", "en_name": "jian1", "ch_name": "䷴漸"}, "54": {"chapter_id": 1, "url": "http://ctext.org/book-of-changes/gui-mei/zh", "en_name": "gui-mei", "ch_name": "䷵歸妹"}, "55": {"chapter_id": 1, "url": "http://ctext.org/book-of-changes/feng/zh", "en_name": "feng", "ch_name": "䷶豐"}, "56": {"chapter_id": 1, "url": "http://ctext.org/book-of-changes/lu1/zh", "en_name": "lu1", "ch_name": "䷷旅"}, "57": {"chapter_id": 1, "url": "http://ctext.org/book-of-changes/xun/zh", "en_name": "xun", "ch_name": "䷸巽"}, "58": {"chapter_id": 1, "url": "http://ctext.org/book-of-changes/dui/zh", "en_name": "dui", "ch_name": "䷹兌"}, "59": {"chapter_id": 1, "url": "http://ctext.org/book-of-changes/huan/zh", "en_name": "huan", "ch_name": "䷺渙"}, "60": {"chapter_id": 1, "url": "http://ctext.org/book-of-changes/jie1/zh", "en_name": "jie1", "ch_name": "䷻節"}, "61": {"chapter_id": 1, "url": "http://ctext.org/book-of-changes/zhong-fu/zh", "en_name": "zhong-fu", "ch_name": "䷼中孚"}, "62": {"chapter_id": 1, "url": "http://ctext.org/book-of-changes/xiao-guo/zh", "en_name": "xiao-guo", "ch_name": "䷽小過"}, "63": {"chapter_id": 1, "url": "http://ctext.org/book-of-changes/ji-ji/zh", "en_name": "ji-ji", "ch_name": "䷾既濟"}, "64": {"chapter_id": 1, "url": "http://ctext.org/book-of-changes/wei-ji/zh", "en_name": "wei-ji", "ch_name": "䷿未濟"}, "65": {"chapter_id": 2, "url": "http://ctext.org/book-of-changes/qian2/zh", "en_name": "qian2", "ch_name": "乾"}, "66": {"chapter_id": 2, "url": "http://ctext.org/book-of-changes/kun2/zh", "en_name": "kun2", "ch_name": "坤"}, "67": {"chapter_id": 2, "url": "http://ctext.org/book-of-changes/zhun1/zh", "en_name": "zhun1", "ch_name": "屯"}, "68": {"chapter_id": 2, "url": "http://ctext.org/book-of-changes/meng1/zh", "en_name": "meng1", "ch_name": "蒙"}, "69": {"chapter_id": 2, "url": "http://ctext.org/book-of-changes/xu1/zh", "en_name": "xu1", "ch_name": "需"}, "70": {"chapter_id": 2, "url": "http://ctext.org/book-of-changes/song1/zh", "en_name": "song1", "ch_name": "訟"}, "71": {"chapter_id": 2, "url": "http://ctext.org/book-of-changes/shi1/zh", "en_name": "shi1", "ch_name": "師"}, "72": {"chapter_id": 2, "url": "http://ctext.org/book-of-changes/bi2/zh", "en_name": "bi2", "ch_name": "比"}, "73": {"chapter_id": 2, "url": "http://ctext.org/book-of-changes/xiao-xu1/zh", "en_name": "xiao-xu1", "ch_name": "小畜"}, "74": {"chapter_id": 2, "url": "http://ctext.org/book-of-changes/lu2/zh", "en_name": "lu2", "ch_name": "履"}, "75": {"chapter_id": 2, "url": "http://ctext.org/book-of-changes/tai1/zh", "en_name": "tai1", "ch_name": "泰"}, "76": {"chapter_id": 2, "url": "http://ctext.org/book-of-changes/pi1/zh", "en_name": "pi1", "ch_name": "否"}, "77": {"chapter_id": 2, "url": "http://ctext.org/book-of-changes/tong-ren1/zh", "en_name": "tong-ren1", "ch_name": "同人"}, "78": {"chapter_id": 2, "url": "http://ctext.org/book-of-changes/da-you1/zh", "en_name": "da-you1", "ch_name": "大有"}, "79": {"chapter_id": 2, "url": "http://ctext.org/book-of-changes/qian3/zh", "en_name": "qian3", "ch_name": "謙"}, "80": {"chapter_id": 2, "url": "http://ctext.org/book-of-changes/yu1/zh", "en_name": "yu1", "ch_name": "豫"}, "81": {"chapter_id": 2, "url": "http://ctext.org/book-of-changes/sui1/zh", "en_name": "sui1", "ch_name": "隨"}, "82": {"chapter_id": 2, "url": "http://ctext.org/book-of-changes/gu1/zh", "en_name": "gu1", "ch_name": "蠱"}, "83": {"chapter_id": 2, "url": "http://ctext.org/book-of-changes/lin1/zh", "en_name": "lin1", "ch_name": "臨"}, "84": {"chapter_id": 2, "url": "http://ctext.org/book-of-changes/guan1/zh", "en_name": "guan1", "ch_name": "觀"}, "85": {"chapter_id": 2, "url": "http://ctext.org/book-of-changes/shi-he1/zh", "en_name": "shi-he1", "ch_name": "噬嗑"}, "86": {"chapter_id": 2, "url": "http://ctext.org/book-of-changes/bi3/zh", "en_name": "bi3", "ch_name": "賁"}, "87": {"chapter_id": 2, "url": "http://ctext.org/book-of-changes/bo1/zh", "en_name": "bo1", "ch_name": "剝"}, "88": {"chapter_id": 2, "url": "http://ctext.org/book-of-changes/fu1/zh", "en_name": "fu1", "ch_name": "復"}, "89": {"chapter_id": 2, "url": "http://ctext.org/book-of-changes/wu-wang1/zh", "en_name": "wu-wang1", "ch_name": "无妄"}, "90": {"chapter_id": 2, "url": "http://ctext.org/book-of-changes/da-xu1/zh", "en_name": "da-xu1", "ch_name": "大畜"}, "91": {"chapter_id": 2, "url": "http://ctext.org/book-of-changes/yi2/zh", "en_name": "yi2", "ch_name": "頤"}, "92": {"chapter_id": 2, "url": "http://ctext.org/book-of-changes/da-guo1/zh", "en_name": "da-guo1", "ch_name": "大過"}, "93": {"chapter_id": 2, "url": "http://ctext.org/book-of-changes/kan1/zh", "en_name": "kan1", "ch_name": "坎"}, "94": {"chapter_id": 2, "url": "http://ctext.org/book-of-changes/li1/zh", "en_name": "li1", "ch_name": "離"}, "95": {"chapter_id": 2, "url": "http://ctext.org/book-of-changes/xian1/zh", "en_name": "xian1", "ch_name": "咸"}, "96": {"chapter_id": 2, "url": "http://ctext.org/book-of-changes/heng1/zh", "en_name": "heng1", "ch_name": "恆"}, "97": {"chapter_id": 2, "url": "http://ctext.org/book-of-changes/dun1/zh", "en_name": "dun1", "ch_name": "遯"}, "98": {"chapter_id": 2, "url": "http://ctext.org/book-of-changes/da-zhuang1/zh", "en_name": "da-zhuang1", "ch_name": "大壯"}, "99": {"chapter_id": 2, "url": "http://ctext.org/book-of-changes/jin1/zh", "en_name": "jin1", "ch_name": "晉"}, "100": {"chapter_id": 2, "url": "http://ctext.org/book-of-changes/ming-yi1/zh", "en_name": "ming-yi1", "ch_name": "明夷"}, "101": {"chapter_id": 2, "url": "http://ctext.org/book-of-changes/jia-ren1/zh", "en_name": "jia-ren1", "ch_name": "家人"}, "102": {"chapter_id": 2, "url": "http://ctext.org/book-of-changes/kui1/zh", "en_name": "kui1", "ch_name": "睽"}, "103": {"chapter_id": 2, "url": "http://ctext.org/book-of-changes/jian2/zh", "en_name": "jian2", "ch_name": "蹇"}, "104": {"chapter_id": 2, "url": "http://ctext.org/book-of-changes/jie2/zh", "en_name": "jie2", "ch_name": "解"}, "105": {"chapter_id": 2, "url": "http://ctext.org/book-of-changes/sun1/zh", "en_name": "sun1", "ch_name": "損"}, "106": {"chapter_id": 2, "url": "http://ctext.org/book-of-changes/yi3/zh", "en_name": "yi3", "ch_name": "益"}, "107": {"chapter_id": 2, "url": "http://ctext.org/book-of-changes/guai1/zh", "en_name": "guai1", "ch_name": "夬"}, "108": {"chapter_id": 2, "url": "http://ctext.org/book-of-changes/gou1/zh", "en_name": "gou1", "ch_name": "姤"}, "109": {"chapter_id": 2, "url": "http://ctext.org/book-of-changes/cui1/zh", "en_name": "cui1", "ch_name": "萃"}, "110": {"chapter_id": 2, "url": "http://ctext.org/book-of-changes/sheng1/zh", "en_name": "sheng1", "ch_name": "升"}, "111": {"chapter_id": 2, "url": "http://ctext.org/book-of-changes/kun3/zh", "en_name": "kun3", "ch_name": "困"}, "112": {"chapter_id": 2, "url": "http://ctext.org/book-of-changes/jing1/zh", "en_name": "jing1", "ch_name": "井"}, "113": {"chapter_id": 2, "url": "http://ctext.org/book-of-changes/ge1/zh", "en_name": "ge1", "ch_name": "革"}, "114": {"chapter_id": 2, "url": "http://ctext.org/book-of-changes/ding1/zh", "en_name": "ding1", "ch_name": "鼎"}, "115": {"chapter_id": 2, "url": "http://ctext.org/book-of-changes/zhen1/zh", "en_name": "zhen1", "ch_name": "震"}, "116": {"chapter_id": 2, "url": "http://ctext.org/book-of-changes/gen1/zh", "en_name": "gen1", "ch_name": "艮"}, "117": {"chapter_id": 2, "url": "http://ctext.org/book-of-changes/jian3/zh", "en_name": "jian3", "ch_name": "漸"}, "118": {"chapter_id": 2, "url": "http://ctext.org/book-of-changes/gui-mei1/zh", "en_name": "gui-mei1", "ch_name": "歸妹"}, "119": {"chapter_id": 2, "url": "http://ctext.org/book-of-changes/feng1/zh", "en_name": "feng1", "ch_name": "豐"}, "120": {"chapter_id": 2, "url": "http://ctext.org/book-of-changes/lu3/zh", "en_name": "lu3", "ch_name": "旅"}, "121": {"chapter_id": 2, "url": "http://ctext.org/book-of-changes/xun1/zh", "en_name": "xun1", "ch_name": "巽"}, "122": {"chapter_id": 2, "url": "http://ctext.org/book-of-changes/dui1/zh", "en_name": "dui1", "ch_name": "兌"}, "123": {"chapter_id": 2, "url": "http://ctext.org/book-of-changes/huan1/zh", "en_name": "huan1", "ch_name": "渙"}, "124": {"chapter_id": 2, "url": "http://ctext.org/book-of-changes/jie3/zh", "en_name": "jie3", "ch_name": "節"}, "125": {"chapter_id": 2, "url": "http://ctext.org/book-of-changes/zhong-fu1/zh", "en_name": "zhong-fu1", "ch_name": "中孚"}, "126": {"chapter_id": 2, "url": "http://ctext.org/book-of-changes/xiao-guo1/zh", "en_name": "xiao-guo1", "ch_name": "小過"}, "127": {"chapter_id": 2, "url": "http://ctext.org/book-of-changes/ji-ji1/zh", "en_name": "ji-ji1", "ch_name": "既濟"}, "128": {"chapter_id": 2, "url": "http://ctext.org/book-of-changes/wei-ji1/zh", "en_name": "wei-ji1", "ch_name": "未濟"}, "129": {"chapter_id": 3, "url": "http://ctext.org/book-of-changes/gan/zh", "en_name": "gan", "ch_name": "乾"}, "130": {"chapter_id": 3, "url": "http://ctext.org/book-of-changes/kun4/zh", "en_name": "kun4", "ch_name": "坤"}, "131": {"chapter_id": 3, "url": "http://ctext.org/book-of-changes/zhun2/zh", "en_name": "zhun2", "ch_name": "屯"}, "132": {"chapter_id": 3, "url": "http://ctext.org/book-of-changes/meng2/zh", "en_name": "meng2", "ch_name": "蒙"}, "133": {"chapter_id": 3, "url": "http://ctext.org/book-of-changes/xu2/zh", "en_name": "xu2", "ch_name": "需"}, "134": {"chapter_id": 3, "url": "http://ctext.org/book-of-changes/song2/zh", "en_name": "song2", "ch_name": "訟"}, "135": {"chapter_id": 3, "url": "http://ctext.org/book-of-changes/shi2/zh", "en_name": "shi2", "ch_name": "師"}, "136": {"chapter_id": 3, "url": "http://ctext.org/book-of-changes/bi4/zh", "en_name": "bi4", "ch_name": "比"}, "137": {"chapter_id": 3, "url": "http://ctext.org/book-of-changes/xiao-chu/zh", "en_name": "xiao-chu", "ch_name": "小畜"}, "138": {"chapter_id": 3, "url": "http://ctext.org/book-of-changes/lv/zh", "en_name": "lv", "ch_name": "履"}, "139": {"chapter_id": 3, "url": "http://ctext.org/book-of-changes/tai2/zh", "en_name": "tai2", "ch_name": "泰"}, "140": {"chapter_id": 3, "url": "http://ctext.org/book-of-changes/fou/zh", "en_name": "fou", "ch_name": "否"}, "141": {"chapter_id": 3, "url": "http://ctext.org/book-of-changes/tong-ren2/zh", "en_name": "tong-ren2", "ch_name": "同人"}, "142": {"chapter_id": 3, "url": "http://ctext.org/book-of-changes/da-you2/zh", "en_name": "da-you2", "ch_name": "大有"}, "143": {"chapter_id": 3, "url": "http://ctext.org/book-of-changes/qian4/zh", "en_name": "qian4", "ch_name": "謙"}, "144": {"chapter_id": 3, "url": "http://ctext.org/book-of-changes/yu2/zh", "en_name": "yu2", "ch_name": "豫"}, "145": {"chapter_id": 3, "url": "http://ctext.org/book-of-changes/sui2/zh", "en_name": "sui2", "ch_name": "隨"}, "146": {"chapter_id": 3, "url": "http://ctext.org/book-of-changes/gu2/zh", "en_name": "gu2", "ch_name": "蠱"}, "147": {"chapter_id": 3, "url": "http://ctext.org/book-of-changes/lin2/zh", "en_name": "lin2", "ch_name": "臨"}, "148": {"chapter_id": 3, "url": "http://ctext.org/book-of-changes/guan2/zh", "en_name": "guan2", "ch_name": "觀"}, "149": {"chapter_id": 3, "url": "http://ctext.org/book-of-changes/shi-ke/zh", "en_name": "shi-ke", "ch_name": "噬嗑"}, "150": {"chapter_id": 3, "url": "http://ctext.org/book-of-changes/bi5/zh", "en_name": "bi5", "ch_name": "賁"}, "151": {"chapter_id": 3, "url": "http://ctext.org/book-of-changes/bo2/zh", "en_name": "bo2", "ch_name": "剝"}, "152": {"chapter_id": 3, "url": "http://ctext.org/book-of-changes/fu2/zh", "en_name": "fu2", "ch_name": "復"}, "153": {"chapter_id": 3, "url": "http://ctext.org/book-of-changes/wu-wang2/zh", "en_name": "wu-wang2", "ch_name": "无妄"}, "154": {"chapter_id": 3, "url": "http://ctext.org/book-of-changes/da-chu/zh", "en_name": "da-chu", "ch_name": "大畜"}, "155": {"chapter_id": 3, "url": "http://ctext.org/book-of-changes/yi4/zh", "en_name": "yi4", "ch_name": "頤"}, "156": {"chapter_id": 3, "url": "http://ctext.org/book-of-changes/da-guo2/zh", "en_name": "da-guo2", "ch_name": "大過"}, "157": {"chapter_id": 3, "url": "http://ctext.org/book-of-changes/kan2/zh", "en_name": "kan2", "ch_name": "坎"}, "158": {"chapter_id": 3, "url": "http://ctext.org/book-of-changes/li2/zh", "en_name": "li2", "ch_name": "離"}, "159": {"chapter_id": 3, "url": "http://ctext.org/book-of-changes/xian2/zh", "en_name": "xian2", "ch_name": "咸"}, "160": {"chapter_id": 3, "url": "http://ctext.org/book-of-changes/heng2/zh", "en_name": "heng2", "ch_name": "恆"}, "161": {"chapter_id": 3, "url": "http://ctext.org/book-of-changes/dun2/zh", "en_name": "dun2", "ch_name": "遯"}, "162": {"chapter_id": 3, "url": "http://ctext.org/book-of-changes/da-zhuang2/zh", "en_name": "da-zhuang2", "ch_name": "大壯"}, "163": {"chapter_id": 3, "url": "http://ctext.org/book-of-changes/jin2/zh", "en_name": "jin2", "ch_name": "晉"}, "164": {"chapter_id": 3, "url": "http://ctext.org/book-of-changes/ming-yi2/zh", "en_name": "ming-yi2", "ch_name": "明夷"}, "165": {"chapter_id": 3, "url": "http://ctext.org/book-of-changes/jia-ren2/zh", "en_name": "jia-ren2", "ch_name": "家人"}, "166": {"chapter_id": 3, "url": "http://ctext.org/book-of-changes/kui2/zh", "en_name": "kui2", "ch_name": "睽"}, "167": {"chapter_id": 3, "url": "http://ctext.org/book-of-changes/jian4/zh", "en_name": "jian4", "ch_name": "蹇"}, "168": {"chapter_id": 3, "url": "http://ctext.org/book-of-changes/jie4/zh", "en_name": "jie4", "ch_name": "解"}, "169": {"chapter_id": 3, "url": "http://ctext.org/book-of-changes/sun2/zh", "en_name": "sun2", "ch_name": "損"}, "170": {"chapter_id": 3, "url": "http://ctext.org/book-of-changes/yi5/zh", "en_name": "yi5", "ch_name": "益"}, "171": {"chapter_id": 3, "url": "http://ctext.org/book-of-changes/guai2/zh", "en_name": "guai2", "ch_name": "夬"}, "172": {"chapter_id": 3, "url": "http://ctext.org/book-of-changes/gou2/zh", "en_name": "gou2", "ch_name": "姤"}, "173": {"chapter_id": 3, "url": "http://ctext.org/book-of-changes/cui2/zh", "en_name": "cui2", "ch_name": "萃"}, "174": {"chapter_id": 3, "url": "http://ctext.org/book-of-changes/sheng2/zh", "en_name": "sheng2", "ch_name": "升"}, "175": {"chapter_id": 3, "url": "http://ctext.org/book-of-changes/kun5/zh", "en_name": "kun5", "ch_name": "困"}, "176": {"chapter_id": 3, "url": "http://ctext.org/book-of-changes/jing2/zh", "en_name": "jing2", "ch_name": "井"}, "177": {"chapter_id": 3, "url": "http://ctext.org/book-of-changes/ge2/zh", "en_name": "ge2", "ch_name": "革"}, "178": {"chapter_id": 3, "url": "http://ctext.org/book-of-changes/ding2/zh", "en_name": "ding2", "ch_name": "鼎"}, "179": {"chapter_id": 3, "url": "http://ctext.org/book-of-changes/zhen2/zh", "en_name": "zhen2", "ch_name": "震"}, "180": {"chapter_id": 3, "url": "http://ctext.org/book-of-changes/gen2/zh", "en_name": "gen2", "ch_name": "艮"}, "181": {"chapter_id": 3, "url": "http://ctext.org/book-of-changes/jian5/zh", "en_name": "jian5", "ch_name": "漸"}, "182": {"chapter_id": 3, "url": "http://ctext.org/book-of-changes/gui-mei2/zh", "en_name": "gui-mei2", "ch_name": "歸妹"}, "183": {"chapter_id": 3, "url": "http://ctext.org/book-of-changes/feng2/zh", "en_name": "feng2", "ch_name": "豐"}, "184": {"chapter_id": 3, "url": "http://ctext.org/book-of-changes/lv1/zh", "en_name": "lv1", "ch_name": "旅"}, "185": {"chapter_id": 3, "url": "http://ctext.org/book-of-changes/xun2/zh", "en_name": "xun2", "ch_name": "巽"}, "186": {"chapter_id": 3, "url": "http://ctext.org/book-of-changes/dui2/zh", "en_name": "dui2", "ch_name": "兌"}, "187": {"chapter_id": 3, "url": "http://ctext.org/book-of-changes/huan2/zh", "en_name": "huan2", "ch_name": "渙"}, "188": {"chapter_id": 3, "url": "http://ctext.org/book-of-changes/jie5/zh", "en_name": "jie5", "ch_name": "節"}, "189": {"chapter_id": 3, "url": "http://ctext.org/book-of-changes/zhong-fu2/zh", "en_name": "zhong-fu2", "ch_name": "中孚"}, "190": {"chapter_id": 3, "url": "http://ctext.org/book-of-changes/xiao-guo2/zh", "en_name": "xiao-guo2", "ch_name": "小過"}, "191": {"chapter_id": 3, "url": "http://ctext.org/book-of-changes/ji-ji2/zh", "en_name": "ji-ji2", "ch_name": "既濟"}, "192": {"chapter_id": 3, "url": "http://ctext.org/book-of-changes/wei-ji2/zh", "en_name": "wei-ji2", "ch_name": "未濟"}, "193": {"chapter_id": 4, "url": "http://ctext.org/book-of-changes/gan1/zh", "en_name": "gan1", "ch_name": "乾"}, "194": {"chapter_id": 4, "url": "http://ctext.org/book-of-changes/kun6/zh", "en_name": "kun6", "ch_name": "坤"}}, "book": {"url": "http://ctext.org/book-of-changes/zh", "type": "tw", "en_name": "book-of-changes", "ch_name": "周易", "categories": [{"en_name": "pre-qin-and-han", "ch_name": "先秦兩漢", "url": "http://ctext.org/pre-qin-and-han/zh", "id": 1}, {"en_name": "ancient-classics", "ch_name": "經典文獻", "url": "http://ctext.org/ancient-classics/zh", "id": 2}], "standalone": false}}