{"chapters": [{"url": "", "ch_name": "", "en_name": "", "id": 1, "articles": [1, 2, 3, 4, 5, 6, 7, 8, 9, 10, 11, 12, 13, 14, 15, 16, 17, 18, 19, 20, 21, 22, 23, 24, 25, 26, 27, 28, 29, 30, 31, 32, 33, 34, 35, 36]}], "articles": {"1": {"chapter_id": 1, "url": "http://ctext.org/qian-fu-lun/zan-xue/zh", "en_name": "zan-xue", "ch_name": "讚學"}, "2": {"chapter_id": 1, "url": "http://ctext.org/qian-fu-lun/wu-ben/zh", "en_name": "wu-ben", "ch_name": "務本"}, "3": {"chapter_id": 1, "url": "http://ctext.org/qian-fu-lun/e-li/zh", "en_name": "e-li", "ch_name": "遏利"}, "4": {"chapter_id": 1, "url": "http://ctext.org/qian-fu-lun/lun-rong/zh", "en_name": "lun-rong", "ch_name": "論榮"}, "5": {"chapter_id": 1, "url": "http://ctext.org/qian-fu-lun/xian-nan/zh", "en_name": "xian-nan", "ch_name": "賢難"}, "6": {"chapter_id": 1, "url": "http://ctext.org/qian-fu-lun/ming-an/zh", "en_name": "ming-an", "ch_name": "明闇"}, "7": {"chapter_id": 1, "url": "http://ctext.org/qian-fu-lun/kao-ji/zh", "en_name": "kao-ji", "ch_name": "考績"}, "8": {"chapter_id": 1, "url": "http://ctext.org/qian-fu-lun/si-xian/zh", "en_name": "si-xian", "ch_name": "思賢"}, "9": {"chapter_id": 1, "url": "http://ctext.org/qian-fu-lun/ben-zheng/zh", "en_name": "ben-zheng", "ch_name": "本政"}, "10": {"chapter_id": 1, "url": "http://ctext.org/qian-fu-lun/qian-tan/zh", "en_name": "qian-tan", "ch_name": "潛歎"}, "11": {"chapter_id": 1, "url": "http://ctext.org/qian-fu-lun/zhong-gui/zh", "en_name": "zhong-gui", "ch_name": "忠貴"}, "12": {"chapter_id": 1, "url": "http://ctext.org/qian-fu-lun/fu-chi/zh", "en_name": "fu-chi", "ch_name": "浮侈"}, "13": {"chapter_id": 1, "url": "http://ctext.org/qian-fu-lun/shen-wei/zh", "en_name": "shen-wei", "ch_name": "慎微"}, "14": {"chapter_id": 1, "url": "http://ctext.org/qian-fu-lun/shi-gong/zh", "en_name": "shi-gong", "ch_name": "實貢"}, "15": {"chapter_id": 1, "url": "http://ctext.org/qian-fu-lun/ban-lu/zh", "en_name": "ban-lu", "ch_name": "班祿"}, "16": {"chapter_id": 1, "url": "http://ctext.org/qian-fu-lun/shu-she/zh", "en_name": "shu-she", "ch_name": "述赦"}, "17": {"chapter_id": 1, "url": "http://ctext.org/qian-fu-lun/san-shi/zh", "en_name": "san-shi", "ch_name": "三式"}, "18": {"chapter_id": 1, "url": "http://ctext.org/qian-fu-lun/ai-ri/zh", "en_name": "ai-ri", "ch_name": "愛日"}, "19": {"chapter_id": 1, "url": "http://ctext.org/qian-fu-lun/duan-song/zh", "en_name": "duan-song", "ch_name": "斷訟"}, "20": {"chapter_id": 1, "url": "http://ctext.org/qian-fu-lun/shuai-zhi/zh", "en_name": "shuai-zhi", "ch_name": "衰制"}, "21": {"chapter_id": 1, "url": "http://ctext.org/qian-fu-lun/quan-jiang/zh", "en_name": "quan-jiang", "ch_name": "勸將"}, "22": {"chapter_id": 1, "url": "http://ctext.org/qian-fu-lun/jiu-bian/zh", "en_name": "jiu-bian", "ch_name": "救邊"}, "23": {"chapter_id": 1, "url": "http://ctext.org/qian-fu-lun/bian-yi/zh", "en_name": "bian-yi", "ch_name": "邊議"}, "24": {"chapter_id": 1, "url": "http://ctext.org/qian-fu-lun/shi-bian/zh", "en_name": "shi-bian", "ch_name": "實邊"}, "25": {"chapter_id": 1, "url": "http://ctext.org/qian-fu-lun/bu-lie/zh", "en_name": "bu-lie", "ch_name": "卜列"}, "26": {"chapter_id": 1, "url": "http://ctext.org/qian-fu-lun/zheng-lie/zh", "en_name": "zheng-lie", "ch_name": "正列"}, "27": {"chapter_id": 1, "url": "http://ctext.org/qian-fu-lun/xiang-lie/zh", "en_name": "xiang-lie", "ch_name": "相列"}, "28": {"chapter_id": 1, "url": "http://ctext.org/qian-fu-lun/meng-lie/zh", "en_name": "meng-lie", "ch_name": "夢列"}, "29": {"chapter_id": 1, "url": "http://ctext.org/qian-fu-lun/shi-nan/zh", "en_name": "shi-nan", "ch_name": "釋難"}, "30": {"chapter_id": 1, "url": "http://ctext.org/qian-fu-lun/jiao-ji/zh", "en_name": "jiao-ji", "ch_name": "交際"}, "31": {"chapter_id": 1, "url": "http://ctext.org/qian-fu-lun/ming-zhong/zh", "en_name": "ming-zhong", "ch_name": "明忠"}, "32": {"chapter_id": 1, "url": "http://ctext.org/qian-fu-lun/ben-xun/zh", "en_name": "ben-xun", "ch_name": "本訓"}, "33": {"chapter_id": 1, "url": "http://ctext.org/qian-fu-lun/de-hua/zh", "en_name": "de-hua", "ch_name": "德化"}, "34": {"chapter_id": 1, "url": "http://ctext.org/qian-fu-lun/wu-de-zhi/zh", "en_name": "wu-de-zhi", "ch_name": "五德志"}, "35": {"chapter_id": 1, "url": "http://ctext.org/qian-fu-lun/zhi-shi-xing/zh", "en_name": "zhi-shi-xing", "ch_name": "志氏姓"}, "36": {"chapter_id": 1, "url": "http://ctext.org/qian-fu-lun/xu-lu/zh", "en_name": "xu-lu", "ch_name": "敘錄"}}, "book": {"url": "http://ctext.org/qian-fu-lun/zh", "type": "tw", "en_name": "qian-fu-lun", "ch_name": "潛夫論", "categories": [{"en_name": "pre-qin-and-han", "ch_name": "先秦兩漢", "url": "http://ctext.org/pre-qin-and-han/zh", "id": 1}, {"en_name": "confucianism", "ch_name": "儒家", "url": "http://ctext.org/confucianism/zh", "id": 2}], "standalone": true}}