{"chapters": [{"url": "", "ch_name": "", "en_name": "", "id": 1, "articles": [1, 2, 3]}], "articles": {"1": {"chapter_id": 1, "url": "http://ctext.org/three-strategies/shang-lve/zh", "en_name": "shang-lve", "ch_name": "上略"}, "2": {"chapter_id": 1, "url": "http://ctext.org/three-strategies/zhong-lve/zh", "en_name": "zhong-lve", "ch_name": "中略"}, "3": {"chapter_id": 1, "url": "http://ctext.org/three-strategies/xia-lve/zh", "en_name": "xia-lve", "ch_name": "下略"}}, "book": {"url": "http://ctext.org/three-strategies/zh", "type": "tw", "en_name": "three-strategies", "ch_name": "三略", "categories": [{"en_name": "pre-qin-and-han", "ch_name": "先秦兩漢", "url": "http://ctext.org/pre-qin-and-han/zh", "id": 1}, {"en_name": "school-of-the-military", "ch_name": "兵家", "url": "http://ctext.org/school-of-the-military/zh", "id": 2}], "standalone": true}}